README
setup.py
ngramgraphs/__init__.py
ngramgraphs/classifier.py
ngramgraphs/datastructures.py
ngramgraphs/draw.py
ngramgraphs/graph.py
ngramgraphs/gui.py
ngramgraphs/similarity.py
ngramgraphs/util.py
ngramgraphs.egg-info/PKG-INFO
ngramgraphs.egg-info/SOURCES.txt
ngramgraphs.egg-info/dependency_links.txt
ngramgraphs.egg-info/requires.txt
ngramgraphs.egg-info/top_level.txt