Metadata-Version: 1.1
Name: ngramgraphs
Version: 0.1.dev250587258
Summary: Create N Gram Graphs and export them to images or PDF files
Home-page: https://gitlab.informatik.uni-bremen.de/sliedtke/ngramgraphs
Author: Simon Liedtke
Author-email: sliedtke@uni-bremen.de
License: UNKNOWN
Platform: UNKNOWN
Classifier: Development Status :: 3 - Alpha
Classifier: Programming Language :: Python :: 3
Classifier: Programming Language :: Python :: 3.4
Classifier: Topic :: Text Processing
